fluidsimfoam-0.0.8.dist-info/METADATA
fluidsimfoam-0.0.8.dist-info/WHEEL
fluidsimfoam-0.0.8.dist-info/entry_points.txt
fluidsimfoam-0.0.8.dist-info/licenses/LICENSE
fluidsimfoam/__init__.py
fluidsimfoam/foam_input_files/__init__.py
fluidsimfoam/foam_input_files/ast.py
fluidsimfoam/foam_input_files/blockmesh/LICENSE
fluidsimfoam/foam_input_files/blockmesh/__init__.py
fluidsimfoam/foam_input_files/blockmesh/edges.py
fluidsimfoam/foam_input_files/blockmesh/grading.py
fluidsimfoam/foam_input_files/constant_files.py
fluidsimfoam/foam_input_files/control_dict.py
fluidsimfoam/foam_input_files/decompose_par.py
fluidsimfoam/foam_input_files/fields.py
fluidsimfoam/foam_input_files/format.py
fluidsimfoam/foam_input_files/fv_options.py
fluidsimfoam/foam_input_files/fv_schemes.py
fluidsimfoam/foam_input_files/generators.py
fluidsimfoam/foam_input_files/grammar.lark
fluidsimfoam/foam_input_files/grammar_advanced.lark
fluidsimfoam/foam_input_files/parser.py
fluidsimfoam/foam_input_files/polymesh.py
fluidsimfoam/foam_input_files/util.py
fluidsimfoam/info.py
fluidsimfoam/init_fields.py
fluidsimfoam/invoke/__init__.py
fluidsimfoam/invoke/context.py
fluidsimfoam/invoke/tasks.py
fluidsimfoam/log.py
fluidsimfoam/make.py
fluidsimfoam/operators.py
fluidsimfoam/output/__init__.py
fluidsimfoam/output/base.py
fluidsimfoam/output/dataframe_from_paths.py
fluidsimfoam/output/fields.py
fluidsimfoam/output/log.py
fluidsimfoam/params.py
fluidsimfoam/resources/LICENSE.template
fluidsimfoam/resources/README.md.template
fluidsimfoam/resources/__init__.py
fluidsimfoam/resources/__init__.py.template
fluidsimfoam/resources/output.py.template
fluidsimfoam/resources/pyproject.toml.template
fluidsimfoam/resources/tasks.py.template
fluidsimfoam/resources/test_generated_solver.py.template
fluidsimfoam/solvers/__init__.py
fluidsimfoam/solvers/base.py
fluidsimfoam/testing.py
fluidsimfoam/util/__init__.py
fluidsimfoam/util/console.py
fluidsimfoam-0.0.8.dist-info/RECORD
