Metadata-Version: 2.1
Name: fluidsimfoam
Version: 0.0.8
Summary: Python framework for OpenFOAM
Author-Email: Pierre Augier <pierre.augier@univ-grenoble-alpes.fr>
License: BSD-3-Clause
Requires-Python: >=3.10
Requires-Dist: fluidsim-core
Requires-Dist: inflection
Requires-Dist: fluiddyn
Requires-Dist: ipython
Requires-Dist: pandas
Requires-Dist: jinja2
Requires-Dist: lark
Requires-Dist: rich
Requires-Dist: invoke
Requires-Dist: pickleshare
Provides-Extra: qt
Requires-Dist: PySide6; extra == "qt"
Provides-Extra: jupyter
Requires-Dist: jupyterlab; extra == "jupyter"
Requires-Dist: jupyterlab-myst; extra == "jupyter"
Requires-Dist: jupytext; extra == "jupyter"
Requires-Dist: mdformat-myst; extra == "jupyter"
Provides-Extra: pyvista
Requires-Dist: pyvista~=0.43.2; extra == "pyvista"
Requires-Dist: vtk~=9.3.0; extra == "pyvista"
